{
	"lessons": {
			"8": {
					"id": 8,
					"name": "Математика",
					"alias": "matematyka",
					"levels": [
							5,
							6,
							7,
							10,
							11,
							12,
							14,
							15,
							17,
							26,
							32,
							41
					]
			},
			"9": {
					"id": 9,
					"name": "Фізика",
					"alias": "fizyka",
					"levels": [
							5,
							6,
							7,
							10,
							11,
							12,
							17,
							26,
							32,
							41
					]
			},
			"10": {
					"id": 10,
					"name": "Українська мова та література",
					"alias": "ukrainska-mova-ta-literatura",
					"levels": [
							5,
							6,
							7,
							10,
							11,
							12,
							14,
							15,
							17,
							19,
							30,
							35
					]
			},
			"11": {
					"id": 11,
					"name": "Хімія",
					"alias": "khimiia",
					"levels": [
							5,
							6,
							7,
							10,
							11,
							12,
							17,
							32
					]
			},
			"12": {
					"id": 12,
					"name": "Біологія",
					"alias": "biolohiia",
					"levels": [
							5,
							6,
							7,
							10,
							11,
							17,
							41
					]
			},
			"13": {
					"id": 13,
					"name": "Англійська мова",
					"alias": "anhliiska-mova",
					"levels": [
							5,
							6,
							7,
							8,
							10,
							11,
							14,
							15,
							17,
							18,
							19,
							20,
							22,
							24,
							25,
							26,
							30,
							31,
							32,
							35,
							40
					]
			},
			"14": {
					"id": 14,
					"name": "Французька мова",
					"alias": "frantsuzka-mova",
					"levels": [
							5,
							6,
							10,
							11,
							17,
							18,
							19,
							20,
							23,
							28,
							30,
							31,
							32,
							35,
							36,
							37
					]
			},
			"15": {
					"id": 15,
					"name": "Німецька мова",
					"alias": "nimetska-mova",
					"levels": [
							5,
							6,
							7,
							10,
							11,
							14,
							15,
							17,
							18,
							19,
							20,
							23,
							27,
							30,
							31,
							32,
							35,
							36,
							37
					]
			},
			"16": {
					"id": 16,
					"name": "Латинь",
					"alias": "latyn",
					"levels": [
							25,
							39
					]
			},
			"17": {
					"id": 17,
					"name": "Давньогрецька мова",
					"alias": "davnohretska-mova",
					"levels": [
							25,
							39
					]
			},
			"19": {
					"id": 19,
					"name": "Історія України",
					"alias": "istoriia-ukrainy",
					"levels": [
							5,
							6,
							7,
							10,
							11,
							17
					]
			},
			"20": {
					"id": 20,
					"name": "Географія",
					"alias": "heohrafiia",
					"levels": [
							5,
							6,
							7,
							10,
							11,
							17
					]
			},
			"21": {
					"id": 21,
					"name": "Італійська мова",
					"alias": "italiiska-mova",
					"levels": [
							5,
							17,
							18,
							19,
							23,
							25,
							30,
							31,
							32,
							35,
							36,
							37
					]
			},
			"22": {
					"id": 22,
					"name": "Польська мова",
					"alias": "polska-mova",
					"levels": [
							11,
							18,
							19,
							20,
							21,
							23,
							25,
							30,
							31,
							32,
							35,
							36,
							37
					]
			},
			"23": {
					"id": 23,
					"name": "Турецька мова",
					"alias": "turetska-mova",
					"levels": [
							18,
							19,
							25,
							30,
							31,
							35
					]
			},
			"24": {
					"id": 24,
					"name": "Грецька мова",
					"alias": "hretska-mova",
					"levels": [
							18,
							19,
							25,
							30,
							31,
							32,
							35
					]
			},
			"25": {
					"id": 25,
					"name": "Всесвітня історія",
					"alias": "vsesvitnia-istoriia",
					"levels": [
							5,
							17
					]
			},
			"26": {
					"id": 26,
					"name": "Програмування",
					"alias": "prohramuvannia",
					"levels": [
							11,
							12,
							17,
							25,
							39,
							42,
							43,
							44,
							45,
							46,
							47
					]
			},
			"27": {
					"id": 27,
					"name": "Креслення",
					"alias": "kreslennia",
					"levels": [
							5,
							11,
							17
					]
			},
			"29": {
					"id": 29,
					"name": "Економіка",
					"alias": "ekonomika",
					"levels": [
							11,
							17
					]
			},
			"30": {
					"id": 30,
					"name": "Живопис",
					"alias": "zhyvopys",
					"levels": [
							18,
							25,
							39
					]
			},
			"31": {
					"id": 31,
					"name": "Малювання",
					"alias": "maliuvannia",
					"levels": [
							18,
							25,
							39
					]
			},
			"32": {
					"id": 32,
					"name": "Психологія",
					"alias": "psykholohiia",
					"levels": [
							11,
							17
					]
			},
			"33": {
					"id": 33,
					"name": "Китайська мова",
					"alias": "kytayska-mova",
					"levels": [
							18,
							19,
							25,
							30,
							31,
							32,
							38
					]
			},
			"35": {
					"id": 35,
					"name": "Гра на гітарі",
					"alias": "uroky-hry-na-hitari",
					"levels": [
							12,
							18,
							25,
							39,
							48
					]
			},
			"36": {
					"id": 36,
					"name": "Гра на фортепіано",
					"alias": "hra-na-fortepiano",
					"levels": [
							12,
							18,
							25,
							39,
							48
					]
			},
			"37": {
					"id": 37,
					"name": "Музика",
					"alias": "muzyka",
					"levels": [
							12,
							18,
							25,
							39,
							48
					]
			},
			"38": {
					"id": 38,
					"name": "Іспанська мова",
					"alias": "ispanska-mova",
					"levels": [
							5,
							6,
							17,
							18,
							19,
							23,
							25,
							29,
							30,
							31,
							32,
							35,
							36,
							37
					]
			},
			"39": {
					"id": 39,
					"name": "Російська мова",
					"alias": "rosiyska-mova",
					"levels": [
							5,
							6,
							15,
							17,
							18,
							19,
							30,
							31,
							35
					]
			},
			"40": {
					"id": 40,
					"name": "Світова література",
					"alias": "Svitova-literatura",
					"levels": [
							5,
							17
					]
			},
			"41": {
					"id": 41,
					"name": "Чеська мова",
					"alias": "cheska-mova",
					"levels": [
							17,
							18,
							19,
							20,
							23,
							25,
							30,
							31,
							32,
							35,
							36,
							37
					]
			},
			"43": {
					"id": 43,
					"name": "Вища математика",
					"alias": "vyshcha-matematyka",
					"levels": [
							11,
							32
					]
			},
			"44": {
					"id": 44,
					"name": "Математичний аналіз",
					"alias": "matematychnyy-analiz",
					"levels": [
							11,
							32
					]
			},
			"45": {
					"id": 45,
					"name": "Фламандська мова",
					"alias": "flamandska-mova",
					"levels": [
							19,
							23,
							25,
							31,
							35,
							36,
							37,
							39
					]
			},
			"46": {
					"id": 46,
					"name": "Акторська майстерність",
					"alias": "aktorska-maysternist",
					"levels": [
							12,
							18,
							25,
							39
					]
			},
			"47": {
					"id": 47,
					"name": "Японська мова",
					"alias": "yaponska-mova",
					"levels": [
							18,
							19,
							25,
							30,
							31,
							32
					]
			},
			"48": {
					"id": 48,
					"name": "Нідерландська мова",
					"alias": "niderlandska-mova",
					"levels": [
							18,
							19,
							23,
							25,
							30,
							31,
							32,
							36,
							37
					]
			},
			"49": {
					"id": 49,
					"name": "Естонська мова",
					"alias": "Estonska-mova",
					"levels": [
							18,
							19,
							20,
							23,
							25,
							30,
							31,
							32,
							35,
							36,
							37
					]
			},
			"50": {
					"id": 50,
					"name": "Підготовка до школи",
					"alias": "pidhotovka-do-shkoly",
					"levels": [
							14,
							18
					]
			},
			"51": {
					"id": 51,
					"name": "Молодші класи",
					"alias": "molodshi-klasy",
					"levels": [
							39,
							41,
							49
					]
			},
			"52": {
					"id": 52,
					"name": "Правознавство",
					"alias": "pravoznavstvo",
					"levels": [
							11,
							17
					]
			},
			"53": {
					"id": 53,
					"name": "Румунська мова",
					"alias": "rumunska-mova",
					"levels": [
							18,
							19,
							20,
							25,
							30,
							31,
							32,
							35
					]
			},
			"54": {
					"id": 54,
					"name": "Норвезька мова",
					"alias": "Norvezka-mova",
					"levels": [
							18,
							19,
							23,
							25,
							30,
							31,
							32,
							35,
							36,
							37
					]
			},
			"55": {
					"id": 55,
					"name": "Угорська мова",
					"alias": "uhorska-mova",
					"levels": [
							18,
							19,
							20,
							25,
							30,
							31,
							32,
							35
					]
			},
			"56": {
					"id": 56,
					"name": "Словацька мова",
					"alias": "slovatska-mova",
					"levels": [
							5,
							17,
							18,
							19,
							20,
							25,
							30,
							31,
							32,
							35
					]
			},
			"57": {
					"id": 57,
					"name": "Філософія",
					"alias": "filosofiya",
					"levels": [
							11,
							17
					]
			},
			"59": {
					"id": 59,
					"name": "Арабська мова",
					"alias": "arabska-mova",
					"levels": [
							18,
							19,
							25,
							30,
							31,
							35
					]
			},
			"60": {
					"id": 60,
					"name": "Португальська мова",
					"alias": "portuhalska-mova",
					"levels": [
							18,
							19,
							20,
							25,
							30,
							31,
							32,
							35
					]
			},
			"61": {
					"id": 61,
					"name": "Астрономія",
					"alias": "astronomiya",
					"levels": [
							10,
							11,
							17
					]
			},
			"62": {
					"id": 62,
					"name": "Няня для дітей",
					"alias": "nyanya-dlya-ditey",
					"levels": [
							14,
							15,
							18
					]
			},
			"63": {
					"id": 63,
					"name": "Фінська мова",
					"alias": "Finska-mova",
					"levels": [
							18,
							19,
							23,
							25,
							30,
							31,
							32,
							35,
							36,
							37
					]
			},
			"64": {
					"id": 64,
					"name": "Хінді",
					"alias": "khindi",
					"levels": [
							19,
							30,
							31,
							39
					]
			},
			"65": {
					"id": 65,
					"name": "Корейська мова",
					"alias": "koreyska-mova",
					"levels": [
							18,
							19,
							25,
							30,
							31,
							32
					]
			},
			"66": {
					"id": 66,
					"name": "Хореографія і танці",
					"alias": "khoreohrafiya-i-tantsi",
					"levels": [
							12,
							18,
							25,
							39
					]
			},
			"67": {
					"id": 67,
					"name": "Уроки вокалу",
					"alias": "uroky-vokalu",
					"levels": [
							18,
							25,
							39
					]
			},
			"68": {
					"id": 68,
					"name": "Вірменська мова",
					"alias": "Virmenska-mova",
					"levels": [
							18,
							19,
							25,
							30,
							31,
							39
					]
			},
			"69": {
					"id": 69,
					"name": "Диференціальні рівняння",
					"alias": "dyferentsialni-rivnyannya",
					"levels": [
							11,
							32
					]
			},
			"70": {
					"id": 70,
					"name": "Теорія ймовірностей",
					"alias": "teoriya-ymovirnostey",
					"levels": [
							11,
							32
					]
			},
			"71": {
					"id": 71,
					"name": "Теоретична механіка",
					"alias": "teoretychna-mekhanika",
					"levels": [
							11,
							32
					]
			},
			"72": {
					"id": 72,
					"name": "Данська мова",
					"alias": "Danska-mova",
					"levels": [
							18,
							19,
							23,
							25,
							30,
							31,
							32,
							35,
							36,
							37
					]
			},
			"73": {
					"id": 73,
					"name": "Розвиток пам'яті",
					"alias": "rozvytok-pamyati",
					"levels": [
							18,
							25,
							39
					]
			},
			"74": {
					"id": 74,
					"name": "Фізичне виховання",
					"alias": "fizychne-vykhovannya",
					"levels": [
							18,
							25,
							39
					]
			},
			"75": {
					"id": 75,
					"name": "Шахи",
					"alias": "shakhy",
					"levels": [
							18,
							25,
							39
					]
			},
			"76": {
					"id": 76,
					"name": "Болгарська мова",
					"alias": "bolharska-mova",
					"levels": [
							19,
							25,
							30,
							31,
							32
					]
			},
			"77": {
					"id": 77,
					"name": "Логопед",
					"alias": "lohopedy",
					"levels": [
							18,
							39
					]
			},
			"78": {
					"id": 78,
					"name": "Хорватська мова",
					"alias": "croatian",
					"levels": [
							19,
							30,
							31,
							35,
							39
					]
			},
			"79": {
					"id": 79,
					"name": "Економічна статистика",
					"alias": "ekonomichna-statystyka",
					"levels": [
							11,
							32
					]
			},
			"80": {
					"id": 80,
					"name": "Фізіологія",
					"alias": "phiziologia",
					"levels": [
							11,
							32
					]
			},
			"81": {
					"id": 81,
					"name": "Ландшафтний дизайн",
					"alias": "landscape",
					"levels": [
							25,
							39
					]
			},
			"82": {
					"id": 82,
					"name": "Сурдопедагог",
					"alias": "surdopedahoh",
					"levels": [
							18,
							25,
							39
					]
			},
			"83": {
					"id": 83,
					"name": "Риторика",
					"alias": "rytoryka",
					"levels": [
							11,
							39
					]
			},
			"84": {
					"id": 84,
					"name": "Політологія",
					"alias": "politolohiya",
					"levels": [
							11
					]
			},
			"85": {
					"id": 85,
					"name": "Графіка",
					"alias": "Hrafika",
					"levels": [
							25,
							39
					]
			},
			"86": {
					"id": 86,
					"name": "Шведська мова",
					"alias": "shvedska-mova",
					"levels": [
							18,
							19,
							23,
							25,
							30,
							31,
							32,
							35,
							36,
							37
					]
			},
			"87": {
					"id": 87,
					"name": "Маркетинг",
					"alias": "marketynh",
					"levels": [
							11
					]
			},
			"88": {
					"id": 88,
					"name": "Фінанси",
					"alias": "finansy",
					"levels": [
							11
					]
			},
			"89": {
					"id": 89,
					"name": "Психолог",
					"alias": "psykholoh",
					"levels": [
							39
					]
			},
			"91": {
					"id": 91,
					"name": "Лінійна алгебра",
					"alias": "lin-algebra",
					"levels": [
							11,
							32
					]
			},
			"92": {
					"id": 92,
					"name": "Аналітична геометрія",
					"alias": "analytic-geometry",
					"levels": [
							11,
							32
					]
			},
			"93": {
					"id": 93,
					"name": "Культурологія",
					"alias": "kult",
					"levels": [
							11,
							17
					]
			},
			"94": {
					"id": 94,
					"name": "Українознавство",
					"alias": "ukrayinoznavstvo",
					"levels": [
							11,
							12
					]
			},
			"95": {
					"id": 95,
					"name": "Азербайджанська мова",
					"alias": "azerbaydzhanska",
					"levels": [
							19,
							25,
							30,
							31,
							39
					]
			},
			"96": {
					"id": 96,
					"name": "Узбецька мова",
					"alias": "Uzbetska-mova",
					"levels": [
							19,
							25,
							30,
							31,
							35
					]
			},
			"97": {
					"id": 97,
					"name": "Білоруська мова",
					"alias": "Biloruska-mova",
					"levels": [
							5,
							11,
							17,
							18,
							19,
							25,
							31,
							35,
							39
					]
			},
			"98": {
					"id": 98,
					"name": "Мова жестів",
					"alias": "mova-zhestiv",
					"levels": [
							18,
							25,
							39
					]
			},
			"99": {
					"id": 99,
					"name": "Інформатика",
					"alias": "informatyka",
					"levels": [
							5,
							11,
							12,
							17
					]
			},
			"100": {
					"id": 100,
					"name": "Сербська мова",
					"alias": "serbian",
					"levels": [
							19,
							30,
							31,
							35,
							39
					]
			},
			"101": {
					"id": 101,
					"name": "Грузинська мова",
					"alias": "georgian",
					"levels": [
							18,
							19,
							25,
							30,
							31,
							39
					]
			},
			"102": {
					"id": 102,
					"name": "Македонська мова",
					"alias": "macedonian",
					"levels": [
							19,
							30,
							31,
							35,
							39
					]
			},
			"103": {
					"id": 103,
					"name": "Боснійська мова",
					"alias": "bosnian",
					"levels": [
							19,
							30,
							31,
							35,
							39
					]
			},
			"104": {
					"id": 104,
					"name": "Каталонська мова",
					"alias": "catalan",
					"levels": [
							11,
							18,
							19,
							25,
							31,
							35,
							39
					]
			},
			"105": {
					"id": 105,
					"name": "Анатомія",
					"alias": "anatomy",
					"levels": [
							11,
							32
					]
			},
			"106": {
					"id": 106,
					"name": "Мистецтвознавство",
					"alias": "hrafika-1",
					"levels": [
							25,
							39
					]
			},
			"107": {
					"id": 107,
					"name": "Юриспруденція",
					"alias": "jurisprudence",
					"levels": [
							11
					]
			},
			"108": {
					"id": 108,
					"name": "Логіка",
					"alias": "shakhy-1",
					"levels": [
							11,
							12,
							17,
							18
					]
			},
			"109": {
					"id": 109,
					"name": "Соціологія",
					"alias": "sociology",
					"levels": [
							11,
							17
					]
			},
			"110": {
					"id": 110,
					"name": "Ботаніка",
					"alias": "botany",
					"levels": [
							11,
							17,
							32
					]
			},
			"111": {
					"id": 111,
					"name": "Зоологія",
					"alias": "zoology",
					"levels": [
							11,
							17,
							32
					]
			},
			"112": {
					"id": 112,
					"name": "Екологія",
					"alias": "ecology",
					"levels": [
							11,
							17
					]
			},
			"113": {
					"id": 113,
					"name": "Генетика",
					"alias": "genetics",
					"levels": [
							11,
							17
					]
			},
			"114": {
					"id": 114,
					"name": "Молекулярна фізика",
					"alias": "molecular_physics",
					"levels": [
							11,
							32
					]
			},
			"115": {
					"id": 115,
					"name": "Електрика і магнетизм",
					"alias": "electrodynamics",
					"levels": [
							11,
							32
					]
			},
			"116": {
					"id": 116,
					"name": "Оптика",
					"alias": "optics",
					"levels": [
							11,
							32
					]
			},
			"117": {
					"id": 117,
					"name": "Казахська мова",
					"alias": "kazakh",
					"levels": [
							19,
							25,
							30,
							31,
							39
					]
			},
			"118": {
					"id": 118,
					"name": "Татарська мова",
					"alias": "tatar",
					"levels": [
							19,
							25,
							30,
							31,
							35
					]
			},
			"119": {
					"id": 119,
					"name": "Гра на саксофоні",
					"alias": "saxophone",
					"levels": [
							12,
							18,
							25,
							39,
							48
					]
			},
			"120": {
					"id": 120,
					"name": "Іврит",
					"alias": "hebrew",
					"levels": [
							19,
							25,
							30,
							31,
							32,
							39
					]
			},
			"121": {
					"id": 121,
					"name": "Гра на скрипці",
					"alias": "violin",
					"levels": [
							12,
							18,
							25,
							39,
							48
					]
			},
			"122": {
					"id": 122,
					"name": "Дизайн",
					"alias": "design",
					"levels": [
							11
					]
			},
			"123": {
					"id": 123,
					"name": "Ісландська мова",
					"alias": "icelandic",
					"levels": [
							18,
							19,
							23,
							25,
							30,
							31,
							32,
							36,
							37
					]
			},
			"124": {
					"id": 124,
					"name": "Словенська мова",
					"alias": "slovenian",
					"levels": [
							19,
							30,
							31,
							35,
							39
					]
			},
			"125": {
					"id": 125,
					"name": "Гра на сопілці, флейті",
					"alias": "sopilka",
					"levels": [
							12,
							18,
							25,
							39,
							48
					]
			},
			"126": {
					"id": 126,
					"name": "Гра на барабанах",
					"alias": "drum",
					"levels": [
							12,
							18,
							25,
							39,
							48
					]
			},
			"127": {
					"id": 127,
					"name": "Гра на трубі",
					"alias": "trumpet",
					"levels": [
							12,
							18,
							25,
							39,
							48
					]
			},
			"128": {
					"id": 128,
					"name": "Журналістика",
					"alias": "journalism",
					"levels": [
							11,
							39
					]
			},
			"129": {
					"id": 129,
					"name": "Інтернет-маркетинг",
					"alias": "internet-marketynh",
					"levels": [
							11,
							12,
							39
					]
			},
			"130": {
					"id": 130,
					"name": "Каліграфія",
					"alias": "calligraphy",
					"levels": [
							25,
							39
					]
			},
			"131": {
					"id": 131,
					"name": "Бухгалтерський облік",
					"alias": "accountancy",
					"levels": [
							11
					]
			},
			"138": {
					"id": 138,
					"name": "Уроки фотошопа (Photoshop)",
					"alias": "photoshop",
					"levels": [
							12,
							25,
							39
					]
			},
			"139": {
					"id": 139,
					"name": "Фарсі (персидська мова)",
					"alias": "farsi",
					"levels": [
							19,
							30,
							31
					]
			},
			"140": {
					"id": 140,
					"name": "Уроки крою та шиття",
					"alias": "uroky-kroyu-ta-shyttya",
					"levels": [
							39
					]
			},
			"141": {
					"id": 141,
					"name": "Фотографія",
					"alias": "fotohrafiya",
					"levels": [
							11,
							12,
							25,
							39
					]
			},
			"142": {
					"id": 142,
					"name": "Фітнес тренер",
					"alias": "fitnes-trener",
					"levels": [
							18,
							25,
							39
					]
			}
	},
	"levels": {
			"5": {
					"id": 5,
					"name": "Шкільна програма 5-9 класи",
					"alias": "shkilna-prohrama"
			},
			"6": {
					"id": 6,
					"name": "Підготовка до ЗНО",
					"alias": "zno"
			},
			"7": {
					"id": 7,
					"name": "Підготовка до ДПА",
					"alias": "dpa"
			},
			"8": {
					"id": 8,
					"name": "TOEFL, IELTS",
					"alias": "toefl-ielts"
			},
			"10": {
					"id": 10,
					"name": "Підготовка до олімпіад",
					"alias": "olimpiada"
			},
			"11": {
					"id": 11,
					"name": "Університетські курси",
					"alias": "university-course"
			},
			"12": {
					"id": 12,
					"name": "Спеціалізовані курси",
					"alias": "spetsializovani-kursy"
			},
			"14": {
					"id": 14,
					"name": "Підготовка до школи",
					"alias": "pidhotovka-do-shkoly-1"
			},
			"15": {
					"id": 15,
					"name": "Молодші класи 1-4",
					"alias": "molodshi-klasy-1-4"
			},
			"17": {
					"id": 17,
					"name": "Шкільна програма 10-11 класи",
					"alias": "shkilna-prohrama-10-11-klasy"
			},
			"18": {
					"id": 18,
					"name": "Репетитор для дітей",
					"alias": "dlya-ditey"
			},
			"19": {
					"id": 19,
					"name": "Розмовна мова",
					"alias": "rozmovnyy-riven"
			},
			"20": {
					"id": 20,
					"name": "До співбесіди в посольстві",
					"alias": "do-spivbesidy-v-posolstvi"
			},
			"21": {
					"id": 21,
					"name": "Співбесіда на карту поляка",
					"alias": "spivbesida-na-kartu-polyaka"
			},
			"22": {
					"id": 22,
					"name": "Рівень А1-А2 (Beginner, Elementary)",
					"alias": "a1-a2-rivni"
			},
			"23": {
					"id": 23,
					"name": "Рівень C1-C2",
					"alias": "c1-c2"
			},
			"24": {
					"id": 24,
					"name": "Рівень B1-B2 (Intermediate)",
					"alias": "b1-b2-rivni"
			},
			"25": {
					"id": 25,
					"name": "Репетитор для початківців",
					"alias": "dlya-pochatkivtsiv"
			},
			"26": {
					"id": 26,
					"name": "GMAT, GRE",
					"alias": "gmat-gre"
			},
			"27": {
					"id": 27,
					"name": "TestDaF, DSD",
					"alias": "testdaf-dsd"
			},
			"28": {
					"id": 28,
					"name": "DELF, DALF, TCF",
					"alias": "delf-dalf-tcf"
			},
			"29": {
					"id": 29,
					"name": "Підготовка до DELE",
					"alias": "dele"
			},
			"30": {
					"id": 30,
					"name": "Ділова та бізнес мова",
					"alias": "dilova"
			},
			"31": {
					"id": 31,
					"name": "Носій мови",
					"alias": "nosiy-movy"
			},
			"32": {
					"id": 32,
					"name": "Підготовка до вступу за кордон",
					"alias": "dlya-vstupu-zakordon"
			},
			"35": {
					"id": 35,
					"name": "Граматика",
					"alias": "hramatyka"
			},
			"36": {
					"id": 36,
					"name": "Рівень А1-А2",
					"alias": "a1-a2"
			},
			"37": {
					"id": 37,
					"name": "Рівень B1-B2",
					"alias": "b1-b2"
			},
			"38": {
					"id": 38,
					"name": "Підготовка до HSK",
					"alias": "hsk-test"
			},
			"39": {
					"id": 39,
					"name": "Базовий рівень",
					"alias": "bazovyy-riven"
			},
			"40": {
					"id": 40,
					"name": "Рівень C1-C2 (Advanced, Proficiency)",
					"alias": "c1-c2-rivni"
			},
			"41": {
					"id": 41,
					"name": "Програма Росток",
					"alias": "rostok"
			},
			"42": {
					"id": 42,
					"name": "Python програмування",
					"alias": "python"
			},
			"43": {
					"id": 43,
					"name": "JavaScript програмування",
					"alias": "javascript"
			},
			"44": {
					"id": 44,
					"name": "C++ програмування",
					"alias": "cplus"
			},
			"45": {
					"id": 45,
					"name": "C# програмування",
					"alias": "csharp"
			},
			"46": {
					"id": 46,
					"name": "PHP програмування",
					"alias": "php"
			},
			"47": {
					"id": 47,
					"name": "Java програмування",
					"alias": "java"
			},
			"48": {
					"id": 48,
					"name": "До вступу в музичні заклади",
					"alias": "muz-education"
			},
			"49": {
					"id": 49,
					"name": "Інтелект України",
					"alias": "intelekt-ukrayiny"
			}
	},
	"rates": {
			"60": {
					"id": 60,
					"name": "60 грн/год",
					"alias": ""
			},
			"70": {
					"id": 70,
					"name": "70 грн/год",
					"alias": ""
			},
			"80": {
					"id": 80,
					"name": "80 грн/год",
					"alias": ""
			},
			"90": {
					"id": 90,
					"name": "90 грн/год",
					"alias": ""
			},
			"100": {
					"id": 100,
					"name": "100 грн/год",
					"alias": ""
			},
			"120": {
					"id": 120,
					"name": "120 грн/год",
					"alias": ""
			},
			"150": {
					"id": 150,
					"name": "150 грн/год",
					"alias": ""
			},
			"170": {
					"id": 170,
					"name": "170 грн/год",
					"alias": ""
			},
			"200": {
					"id": 200,
					"name": "200 грн/год",
					"alias": ""
			},
			"250": {
					"id": 250,
					"name": "250 грн/год",
					"alias": ""
			},
			"300": {
					"id": 300,
					"name": "300 грн/год",
					"alias": ""
			},
			"400": {
					"id": 400,
					"name": "400 грн/год",
					"alias": ""
			},
			"500": {
					"id": 500,
					"name": "500 грн/год",
					"alias": ""
			},
			"600": {
					"id": 600,
					"name": "600 грн/год",
					"alias": ""
			}
	},
	"practices": {
			"11": {
					"id": 11,
					"name": "менше 1 року",
					"alias": ""
			},
			"12": {
					"id": 12,
					"name": "більше 1 року",
					"alias": ""
			},
			"13": {
					"id": 13,
					"name": "більше 2 років",
					"alias": ""
			},
			"14": {
					"id": 14,
					"name": "більше 3 років",
					"alias": ""
			},
			"15": {
					"id": 15,
					"name": "більше 5 років",
					"alias": ""
			},
			"17": {
					"id": 17,
					"name": "більше 10 років",
					"alias": ""
			},
			"18": {
					"id": 18,
					"name": "більше 20 років",
					"alias": ""
			}
	},
	"universities": {
			"607": {
					"id": 607,
					"name": "Азовський морський інститут Одеської національної морської академії (АМІ ОНМА)",
					"alias": ""
			},
			"608": {
					"id": 608,
					"name": "Академія внутрішніх військ МВС України (АВВУ)",
					"alias": ""
			},
			"609": {
					"id": 609,
					"name": "Бердянський державний педагогічний університет (БДПУ)",
					"alias": ""
			},
			"610": {
					"id": 610,
					"name": "Бережанський агротехнічний інститут НУБіП",
					"alias": ""
			},
			"611": {
					"id": 611,
					"name": "Білоцерківський національний аграрний університет (БНАУ)",
					"alias": ""
			},
			"612": {
					"id": 612,
					"name": "ВДНЗ України \"Буковинський державний медичний університет\"",
					"alias": ""
			},
			"613": {
					"id": 613,
					"name": "Видавничо-поліграфічний інститут НТУУ \"КПІ\"",
					"alias": ""
			},
			"614": {
					"id": 614,
					"name": "Вищий навчальний заклад «Міжнародний технологічний університет «Миколаївська політехніка»",
					"alias": ""
			},
			"615": {
					"id": 615,
					"name": "Військовий інститут телекомунікацій та інформатизації Державного університету телекомунікацій (ВІТІ ДУТ)",
					"alias": ""
			},
			"616": {
					"id": 616,
					"name": "Вінницька філія (ННВЦ) Одеської національної академії зв'язку (ОНАЗ)",
					"alias": ""
			},
			"617": {
					"id": 617,
					"name": "Вінницький державний педагогічний університет ім. М. Коцюбинського (ВДПУ)",
					"alias": ""
			},
			"618": {
					"id": 618,
					"name": "Вінницький кооперативний інститут (ВКІ)",
					"alias": ""
			},
			"619": {
					"id": 619,
					"name": "Вінницький навчально-науковий інститут УДФСУ",
					"alias": ""
			},
			"620": {
					"id": 620,
					"name": "Вінницький національний аграрний університет (ВНАУ)",
					"alias": ""
			},
			"621": {
					"id": 621,
					"name": "Вінницький національний медичний університет ім. М. Пирогова (ВНМУ)",
					"alias": ""
			},
			"622": {
					"id": 622,
					"name": "Вінницький національний технічний університет (ВНТУ)",
					"alias": ""
			},
			"623": {
					"id": 623,
					"name": "Вінницький торговельно-економічний інститут КНТЕУ",
					"alias": ""
			},
			"624": {
					"id": 624,
					"name": "ВП НУБіП України \"Ірпінський економічний коледж\"",
					"alias": ""
			},
			"625": {
					"id": 625,
					"name": "Глухівський національний педагогічний університет ім. Довженка (ГНПУ)",
					"alias": ""
			},
			"626": {
					"id": 626,
					"name": "Горлівський інститут іноземних мов Державного вищого навчального закладу «Донбаський державний педагогічний університет»",
					"alias": ""
			},
			"627": {
					"id": 627,
					"name": "ДВНЗ «Переяслав-Хмельницький державний педагогічний університет імені Григорія Сковороди»",
					"alias": ""
			},
			"628": {
					"id": 628,
					"name": "Державний вищий навчальний заклад \"Університет банківської справи\"",
					"alias": ""
			},
			"629": {
					"id": 629,
					"name": "Державний університет інфраструктури та технологій (ДУІТ)",
					"alias": ""
			},
			"630": {
					"id": 630,
					"name": "Державний університет телекомунікацій (ДУТ)",
					"alias": ""
			},
			"631": {
					"id": 631,
					"name": "ДЗ \"Луганський державний медичний університет\" (ДЗ \"ЛДМУ\")",
					"alias": ""
			},
			"632": {
					"id": 632,
					"name": "Дніпровський державний аграрно-економічний університет",
					"alias": ""
			},
			"633": {
					"id": 633,
					"name": "Дніпровський державний технічний університет (ДДТУ)",
					"alias": ""
			},
			"634": {
					"id": 634,
					"name": "Дніпровський національний університет імені Олеся Гончара (ДНУ)",
					"alias": ""
			},
			"635": {
					"id": 635,
					"name": "Дніпропетровська консерваторія імені М. Глінки",
					"alias": ""
			},
			"636": {
					"id": 636,
					"name": "Дніпропетровська медична академія (ДМА)",
					"alias": ""
			},
			"637": {
					"id": 637,
					"name": "Дніпропетровський державний університет внутрішніх справ",
					"alias": ""
			},
			"638": {
					"id": 638,
					"name": "Дніпропетровський національний університет залізничного транспорту ім. В. Лазаряна (ДНУЗТ)",
					"alias": ""
			},
			"639": {
					"id": 639,
					"name": "Дніпропетровський регіональний інститут державного управління НАДУ",
					"alias": ""
			},
			"640": {
					"id": 640,
					"name": "Донбаська державна машинобудівна академія (ДДМА)",
					"alias": ""
			},
			"641": {
					"id": 641,
					"name": "Донбаська національна академія будівництва і архітектури (ДонНАБА)",
					"alias": ""
			},
			"642": {
					"id": 642,
					"name": "Донбаський державний педагогічний університет (ДДПУ)",
					"alias": ""
			},
			"643": {
					"id": 643,
					"name": "Донбаський державний технічний університет (ДонДТУ)",
					"alias": ""
			},
			"644": {
					"id": 644,
					"name": "Донецька державна музична академія імені Прокоф'єва (ДонДМА)",
					"alias": ""
			},
			"645": {
					"id": 645,
					"name": "Донецький державний університет управління (ДДУУ)",
					"alias": ""
			},
			"646": {
					"id": 646,
					"name": "Донецький інститут залізничного транспорту УДАЗТ",
					"alias": ""
			},
			"647": {
					"id": 647,
					"name": "Донецький інститут міського господарства Київського університету управління та підприємництва (ДІМГ)",
					"alias": ""
			},
			"648": {
					"id": 648,
					"name": "Донецький національний медичний університет (ДонНМУ)",
					"alias": ""
			},
			"649": {
					"id": 649,
					"name": "Донецький національний медичний університет",
					"alias": ""
			},
			"650": {
					"id": 650,
					"name": "Донецький національний технічний університет (ДонНТУ)",
					"alias": ""
			},
			"651": {
					"id": 651,
					"name": "Донецький національний університет економіки і торгівлі імені Михайла Туган-Барановського (ДонНУЕТ)",
					"alias": ""
			},
			"652": {
					"id": 652,
					"name": "Донецький національний університет імені Василя Стуса (ДонНУ імені Василя Стуса)",
					"alias": ""
			},
			"653": {
					"id": 653,
					"name": "Донецький юридичний інститут МВС України",
					"alias": ""
			},
			"654": {
					"id": 654,
					"name": "Дрогобицький державний педагогічний університет ім. Франка (ДДПУ)",
					"alias": ""
			},
			"655": {
					"id": 655,
					"name": "Євпаторійське відділення Кримського факультету Східноукраїнського національного університету ім. Даля",
					"alias": ""
			},
			"656": {
					"id": 656,
					"name": "Євпаторійський інститут соціальних наук КГУ",
					"alias": ""
			},
			"657": {
					"id": 657,
					"name": "Житомирський військовий інститут імені С. П. Корольова (ЖВІ)",
					"alias": ""
			},
			"658": {
					"id": 658,
					"name": "Житомирський державний технологічний університет (ЖДТУ)",
					"alias": ""
			},
			"659": {
					"id": 659,
					"name": "Житомирський державний університет ім. Франка (ЖДУ)",
					"alias": ""
			},
			"660": {
					"id": 660,
					"name": "Житомирський інститут культури і мистецтв (ЖІКМ)",
					"alias": ""
			},
			"661": {
					"id": 661,
					"name": "Житомирський національний агроекологічний університет (ЖНАУ)",
					"alias": ""
			},
			"662": {
					"id": 662,
					"name": "Закарпатська академія мистецтв",
					"alias": ""
			},
			"663": {
					"id": 663,
					"name": "Закарпатський НКЦ Національного університету водного господарства та природокористування",
					"alias": ""
			},
			"664": {
					"id": 664,
					"name": "Запорізька державна інженерна академія (ЗДІА)",
					"alias": ""
			},
			"665": {
					"id": 665,
					"name": "Запорізький державний медичний університет (ЗДМУ)",
					"alias": ""
			},
			"666": {
					"id": 666,
					"name": "Запорізький національний технічний університет (ЗНТУ)",
					"alias": ""
			},
			"667": {
					"id": 667,
					"name": "Запорізький національний університет (ЗНУ)",
					"alias": ""
			},
			"668": {
					"id": 668,
					"name": "Запорізький юридичний інститут Дніпропетровського державного університету внутрішніх справ (ЗЮІ ДДУВС)",
					"alias": ""
			},
			"669": {
					"id": 669,
					"name": "Івано-Франківський національний медичний університет (ІФНМУ)",
					"alias": ""
			},
			"670": {
					"id": 670,
					"name": "Івано-Франківський національний технічний університет нафти і газу (ІФНТУНГ)",
					"alias": ""
			},
			"671": {
					"id": 671,
					"name": "Ізмаїльський державний гуманітарний університет (ІДГУ)",
					"alias": ""
			},
			"672": {
					"id": 672,
					"name": "Ізмаїльський інститут водного транспорту (ІІВТ)",
					"alias": ""
			},
			"673": {
					"id": 673,
					"name": "Інститут банківських технологій та бізнесу ДВНЗ \"Університет банківської справи\"",
					"alias": ""
			},
			"674": {
					"id": 674,
					"name": "Інститут інтегрованих форм навчання НМетАУ",
					"alias": ""
			},
			"675": {
					"id": 675,
					"name": "Інститут інтелектуальної власності НУ \"Одеська юридична академія\"",
					"alias": ""
			},
			"676": {
					"id": 676,
					"name": "Інститут міжнародних відносин Київського національного університету імені Тараса Шевченка",
					"alias": ""
			},
			"677": {
					"id": 677,
					"name": "Інститут підготовки кадрів державної служби зайнятості України (ІПК ДСЗУ)",
					"alias": ""
			},
			"678": {
					"id": 678,
					"name": "Інститут підприємництва \"Стратегія\"",
					"alias": ""
			},
			"679": {
					"id": 679,
					"name": "Інститут післядипломної освіти інженерно-педагогічних працівників ДВНЗ \"Університет менеджменту освіти\"",
					"alias": ""
			},
			"680": {
					"id": 680,
					"name": "Інститут туризму Федерації профспілок України (ІТ ФПУ)",
					"alias": ""
			},
			"681": {
					"id": 681,
					"name": "Інститут Управління державної охорони України",
					"alias": ""
			},
			"682": {
					"id": 682,
					"name": "Інститут управління і права Національного юридичного університету імені Ярослава Мудрого",
					"alias": ""
			},
			"683": {
					"id": 683,
					"name": "Інститут хімічних технологій СНУ",
					"alias": ""
			},
			"684": {
					"id": 684,
					"name": "Кам'янець-Подільський національний університет імені Івана Огієнка (К-ПНУ)",
					"alias": ""
			},
			"685": {
					"id": 685,
					"name": "Кафедра військової підготовки ІФНТУНГ",
					"alias": ""
			},
			"686": {
					"id": 686,
					"name": "Керченський державний морський технологічний університет (КДМТУ)",
					"alias": ""
			},
			"687": {
					"id": 687,
					"name": "Керченський економіко-гуманітарний інститут Таврійського національного университету ім. Вернадського (КЕГІ ТНУ)",
					"alias": ""
			},
			"688": {
					"id": 688,
					"name": "Київська державна академія водного транспорту ім. Конашевича-Сагайдачного (КДАВТ Дунайський НКП)",
					"alias": ""
			},
			"689": {
					"id": 689,
					"name": "Київська державна академія водного транспорту ім. Конашевича-Сагайдачного (КДАВТ)",
					"alias": ""
			},
			"690": {
					"id": 690,
					"name": "Київська муніципальна академія естрадного та циркового мистецтв",
					"alias": ""
			},
			"691": {
					"id": 691,
					"name": "Київський державний інститут декоративно-прикладного мистецтва і дизайну ім. Бойчука (КДІ ДПМД)",
					"alias": ""
			},
			"692": {
					"id": 692,
					"name": "Київський інститут музики ім. Р. М. Глієра",
					"alias": ""
			},
			"693": {
					"id": 693,
					"name": "Київський національний економічний університет ім. Вадима Гетьмана (КНЕУ)",
					"alias": ""
			},
			"694": {
					"id": 694,
					"name": "Київський національний лінгвістичний університет (КНЛУ)",
					"alias": ""
			},
			"695": {
					"id": 695,
					"name": "Київський національний торговельно-економічний університет (КНТЕУ)",
					"alias": ""
			},
			"696": {
					"id": 696,
					"name": "Київський національний університет будівництва і архітектури (КНУБА)",
					"alias": ""
			},
			"697": {
					"id": 697,
					"name": "Київський національний університет імені Тараса Шевченка (КНУ)",
					"alias": ""
			},
			"698": {
					"id": 698,
					"name": "Київський національний університет культури і мистецтв (КНУКіМ)",
					"alias": ""
			},
			"699": {
					"id": 699,
					"name": "Київський національний університет театру",
					"alias": ""
			},
			"700": {
					"id": 700,
					"name": "Київський національний університет технологій та дизайну (КНУТД)",
					"alias": ""
			},
			"701": {
					"id": 701,
					"name": "Київський університет імені Бориса Грінченка",
					"alias": ""
			},
			"702": {
					"id": 702,
					"name": "Київський університет культури і мистецтв (Миколаївський факультет менеджменту і бізнесу)",
					"alias": ""
			},
			"703": {
					"id": 703,
					"name": "Київський університет права НАН України (КУП НАНУ)",
					"alias": ""
			},
			"704": {
					"id": 704,
					"name": "Київський університет ринкових відносин (КУРВ)",
					"alias": ""
			},
			"705": {
					"id": 705,
					"name": "Кіровоградська льотна академія НАУ",
					"alias": ""
			},
			"706": {
					"id": 706,
					"name": "Кіровоградський державний педагогічний університет ім. Винниченка (КДПУ)",
					"alias": ""
			},
			"707": {
					"id": 707,
					"name": "Комунальний вищий навчальний заклад «Хортицька національна навчально-реабілітаційна академія»",
					"alias": ""
			},
			"708": {
					"id": 708,
					"name": "Косівський інститут прикладного та декоративного мистецтва Львівської національної академії мистецтв (КІПДМ ЛНАМ)",
					"alias": ""
			},
			"709": {
					"id": 709,
					"name": "Костянтинівська філія Донецького національного університету імені Василя Стуса",
					"alias": ""
			},
			"710": {
					"id": 710,
					"name": "Красноармійський індустріальний інститут \"Донецький національний технічний університет\" (КІІ ДонНТУ)",
					"alias": ""
			},
			"711": {
					"id": 711,
					"name": "Краснодонський факультет інженерії та менеджменту Східноукраїнського національного університету ім. В. Даля",
					"alias": ""
			},
			"712": {
					"id": 712,
					"name": "Кременецька обласна гуманітарно-педагогічна академія ім. Тараса Шевченка (КОГПА)",
					"alias": ""
			},
			"713": {
					"id": 713,
					"name": "Кременчуцький національний університет імені Михайла Остроградського",
					"alias": ""
			},
			"714": {
					"id": 714,
					"name": "Криворізький економічний інститут \"Київський національний економічний університет імені Вадима Гетьмана\" (КЕІ КНЕУ)",
					"alias": ""
			},
			"715": {
					"id": 715,
					"name": "Криворізький національний університет",
					"alias": ""
			},
			"716": {
					"id": 716,
					"name": "Криворізький педагогічний інститут КНУ",
					"alias": ""
			},
			"717": {
					"id": 717,
					"name": "Кримський агротехнологічний університет (КАТУ)",
					"alias": ""
			},
			"718": {
					"id": 718,
					"name": "Кримський гуманітарний університет (КГУ)",
					"alias": ""
			},
			"719": {
					"id": 719,
					"name": "Кримський державний медичний університет ім. Георгієвського (КДМУ)",
					"alias": ""
			},
			"720": {
					"id": 720,
					"name": "Кримський економічний інститут КНЕУ",
					"alias": ""
			},
			"721": {
					"id": 721,
					"name": "Кримський інженерно-педагогічний університет (Джанкойський НКП)",
					"alias": ""
			},
			"722": {
					"id": 722,
					"name": "Кримський інженерно-педагогічний університет (Євпаторійський НКП)",
					"alias": ""
			},
			"723": {
					"id": 723,
					"name": "Кримський інженерно-педагогічний університет (Керченський НКП)",
					"alias": ""
			},
			"724": {
					"id": 724,
					"name": "Кримський інженерно-педагогічний університет (КІПУ)",
					"alias": ""
			},
			"725": {
					"id": 725,
					"name": "Кримський НКЦ Національного університету водного господарства та природокористування",
					"alias": ""
			},
			"726": {
					"id": 726,
					"name": "Лівадійське відділення Кримського факультету СНУ",
					"alias": ""
			},
			"727": {
					"id": 727,
					"name": "Луганська державна академія культури і мистецтв (ЛДАКМ)",
					"alias": ""
			},
			"728": {
					"id": 728,
					"name": "Луганський державний інститут житлово-комунального господарства і будівництва (ЛДІ ЖКГіБ)",
					"alias": ""
			},
			"729": {
					"id": 729,
					"name": "Луганський державний університет внутрішніх справ ім. Дідоренка (ЛДУВС)",
					"alias": ""
			},
			"730": {
					"id": 730,
					"name": "Луганський інститут праці та соціальних технологій (ЛІПСТ)",
					"alias": ""
			},
			"731": {
					"id": 731,
					"name": "Луганський національний аграрний університет (ЛНАУ)",
					"alias": ""
			},
			"732": {
					"id": 732,
					"name": "Луганський національний університет ім. Шевченка (ЛНУ)",
					"alias": ""
			},
			"733": {
					"id": 733,
					"name": "Луцький національний технічний університет (Луцький НТУ)",
					"alias": ""
			},
			"734": {
					"id": 734,
					"name": "Львівська державна фінансова академія (ЛДФА)",
					"alias": ""
			},
			"735": {
					"id": 735,
					"name": "Львівська національна академія мистецтв (ЛНАМ)",
					"alias": ""
			},
			"736": {
					"id": 736,
					"name": "Львівська національна музична академія ім. Лисенка (ЛНМА)",
					"alias": ""
			},
			"737": {
					"id": 737,
					"name": "Львівський державний університет безпеки життєдіяльності (ЛДУ БЖД)",
					"alias": ""
			},
			"738": {
					"id": 738,
					"name": "Львівський державний університет внутрішніх справ (ЛьвДУВС)",
					"alias": ""
			},
			"739": {
					"id": 739,
					"name": "Львівський державний університет фізичної культури (ЛДУФК)",
					"alias": ""
			},
			"740": {
					"id": 740,
					"name": "Львівський інститут економіки і туризму (ЛІЕТ)",
					"alias": ""
			},
			"741": {
					"id": 741,
					"name": "Львівський навчально-науковий інститут ДВНЗ \"Університет банківської справи\"",
					"alias": ""
			},
			"742": {
					"id": 742,
					"name": "Львівський національний аграрний університет (ЛНАУ)",
					"alias": ""
			},
			"743": {
					"id": 743,
					"name": "Львівський національний медичний університет ім.Данила Галицького (ЛНМУ)",
					"alias": ""
			},
			"744": {
					"id": 744,
					"name": "Львівський національний університет ветеринарної медицини та біотехнологій ім. Ґжицького (ЛНУВМ та БТ)",
					"alias": ""
			},
			"745": {
					"id": 745,
					"name": "Львівський національний університет ім. Франка (ЛНУ)",
					"alias": ""
			},
			"746": {
					"id": 746,
					"name": "Львівський регіональний інститут державного управління НАДУ",
					"alias": ""
			},
			"747": {
					"id": 747,
					"name": "Львівський торговельно-економічний університет",
					"alias": ""
			},
			"748": {
					"id": 748,
					"name": "Маріупольська філія Донецького національного університету імені Василя Стуса",
					"alias": ""
			},
			"749": {
					"id": 749,
					"name": "Маріупольський державний університет (МДУ)",
					"alias": ""
			},
			"750": {
					"id": 750,
					"name": "Мелітопольський державний педагогічний університет ім. Б. Хмельницького (МДПУ)",
					"alias": ""
			},
			"751": {
					"id": 751,
					"name": "Миколаївська філія Київського національного університета культури і мистецтв",
					"alias": ""
			},
			"752": {
					"id": 752,
					"name": "Миколаївський навчально-науковий інститут Одеського національного університету ім. Мечникова (МННІ ОНУ)",
					"alias": ""
			},
			"753": {
					"id": 753,
					"name": "Миколаївський національний аграрний університет (МНАУ)",
					"alias": ""
			},
			"754": {
					"id": 754,
					"name": "Миколаївський національний університет ім. Сухомлинського (МНУ)",
					"alias": ""
			},
			"755": {
					"id": 755,
					"name": "Мукачівський державний університет (МДУ)",
					"alias": ""
			},
			"756": {
					"id": 756,
					"name": "Навчально-методичний комплекс \"Інститут післядипломної освіти\" КПІ ім. Ігоря Сікорського",
					"alias": ""
			},
			"757": {
					"id": 757,
					"name": "Навчально-науковий інститут інформаційної безпеки Національної академії СБУ",
					"alias": ""
			},
			"758": {
					"id": 758,
					"name": "Навчально-науковий інститут підготовки кадрів громадської безпеки та психологічної служби",
					"alias": ""
			},
			"759": {
					"id": 759,
					"name": "Навчально-науковий професійно-педагогічний інститут м. Артемівськ",
					"alias": ""
			},
			"760": {
					"id": 760,
					"name": "Національна академія внутрішніх справ (НАВС)",
					"alias": ""
			},
			"761": {
					"id": 761,
					"name": "Національна академія державного управління при Президентові України (НАДУ)",
					"alias": ""
			},
			"762": {
					"id": 762,
					"name": "Національна академія Державної прикордонної служби України ім. Хмельницького (НАДПСУ)",
					"alias": ""
			},
			"763": {
					"id": 763,
					"name": "Національна академія керівних кадрів культури і мистецтв (НАКККіМ)",
					"alias": ""
			},
			"764": {
					"id": 764,
					"name": "Національна академія образотворчого мистецтва і архітектури (НАОМА)",
					"alias": ""
			},
			"765": {
					"id": 765,
					"name": "Національна академія природоохоронного та курортного будівництва (НАПКБ)",
					"alias": ""
			},
			"766": {
					"id": 766,
					"name": "Національна академія Служби безпеки України",
					"alias": ""
			},
			"767": {
					"id": 767,
					"name": "Національна академія сухопутних військ ім. Сагайдачного (НАСВ)",
					"alias": ""
			},
			"768": {
					"id": 768,
					"name": "Національна медична академія післядипломної освіти імені П. Л. Шупика (НМАПО)",
					"alias": ""
			},
			"769": {
					"id": 769,
					"name": "Національна металургійна академія України (НМетАУ)",
					"alias": ""
			},
			"770": {
					"id": 770,
					"name": "Національна музична академія України ім. Чайковського (НМАУ)",
					"alias": ""
			},
			"771": {
					"id": 771,
					"name": "Національний авіаційний університет (НАУ)",
					"alias": ""
			},
			"772": {
					"id": 772,
					"name": "Національний аерокосмічний університет ім. М.Є. Жуковського «Харківський авіаційний інститут»",
					"alias": ""
			},
			"773": {
					"id": 773,
					"name": "Національний лісотехнічний університет України (НЛТУ України)",
					"alias": ""
			},
			"774": {
					"id": 774,
					"name": "Національний медичний університет ім. Богомольця (НМУ)",
					"alias": ""
			},
			"775": {
					"id": 775,
					"name": "Національний педагогічний університет імені М. П. Драгоманова (НПУ)",
					"alias": ""
			},
			"776": {
					"id": 776,
					"name": "Національний технічний університет \"Дніпровська політехніка\" (НТУ \"ДП\")",
					"alias": ""
			},
			"777": {
					"id": 777,
					"name": "Національний технічний університет \"Харківський політехнічний інститут\" (НТУ ХПІ)",
					"alias": ""
			},
			"778": {
					"id": 778,
					"name": "Національний технічний університет України \"Київський політехнічний інститут\" (НТУУ КПІ)",
					"alias": ""
			},
			"779": {
					"id": 779,
					"name": "Національний транспортний університет (НТУ)",
					"alias": ""
			},
			"780": {
					"id": 780,
					"name": "Національний університет \"Києво-Могилянська академія\" (НаУКМА)",
					"alias": ""
			},
			"781": {
					"id": 781,
					"name": "Національний університет \"Одеська морська академія\" (НУ ОМА)",
					"alias": ""
			},
			"782": {
					"id": 782,
					"name": "Національний університет \"Одеська юридична академія\"",
					"alias": ""
			},
			"783": {
					"id": 783,
					"name": "Національний університет \"Острозька академія\"",
					"alias": ""
			},
			"784": {
					"id": 784,
					"name": "Національний університет «Львівська політехніка» (НУ «ЛП»)",
					"alias": ""
			},
			"785": {
					"id": 785,
					"name": "Національний університет біоресурсів і природокористування України (НУБПУ)",
					"alias": ""
			},
			"786": {
					"id": 786,
					"name": "Національний університет водного господарства та природокористування (НУВГП)",
					"alias": ""
			},
			"787": {
					"id": 787,
					"name": "Національний університет кораблебудування ім. Макарова (НУК)",
					"alias": ""
			},
			"788": {
					"id": 788,
					"name": "Національний університет фізичного виховання і спорту України (НУФВС)",
					"alias": ""
			},
			"789": {
					"id": 789,
					"name": "Національний університет харчових технологій (НУХТ)",
					"alias": ""
			},
			"790": {
					"id": 790,
					"name": "Національний університет цивільного захисту України (НУЦЗУ)",
					"alias": ""
			},
			"791": {
					"id": 791,
					"name": "Національний фармацевтичний університет (НФаУ)",
					"alias": ""
			},
			"792": {
					"id": 792,
					"name": "Національний юридичний університет імені Ярослава Мудрого",
					"alias": ""
			},
			"793": {
					"id": 793,
					"name": "Ніжинський агротехнічний інститут Національного університету біоресурсів і природокористування України",
					"alias": ""
			},
			"794": {
					"id": 794,
					"name": "Ніжинський державний університет ім. Гоголя (НДУ)",
					"alias": ""
			},
			"795": {
					"id": 795,
					"name": "Одеська державна академія будівництва та архітектури (ОДАБА)",
					"alias": ""
			},
			"796": {
					"id": 796,
					"name": "Одеська державна академія технічного регулювання та якості (ОДАТРтаЯ)",
					"alias": ""
			},
			"797": {
					"id": 797,
					"name": "Одеська національна академія зв'язку ім. О.С. Попова (ОНАЗ)",
					"alias": ""
			},
			"798": {
					"id": 798,
					"name": "Одеська національна академія харчових технологій (ОНАХТ)",
					"alias": ""
			},
			"799": {
					"id": 799,
					"name": "Одеська національна музична академія ім. Нежданової (ОДМА)",
					"alias": ""
			},
			"800": {
					"id": 800,
					"name": "Одеський державний аграрний університет (ОДАУ)",
					"alias": ""
			},
			"801": {
					"id": 801,
					"name": "Одеський державний екологічний університет (ОДЕКУ)",
					"alias": ""
			},
			"802": {
					"id": 802,
					"name": "Одеський державний університет внутрішніх справ (ОДУВС)",
					"alias": ""
			},
			"803": {
					"id": 803,
					"name": "Одеський національний економічний університет (ОНЕУ)",
					"alias": ""
			},
			"804": {
					"id": 804,
					"name": "Одеський національний медичний університет (ОНМУ)",
					"alias": ""
			},
			"805": {
					"id": 805,
					"name": "Одеський національний морський університет (ОНМУ)",
					"alias": ""
			},
			"806": {
					"id": 806,
					"name": "Одеський національний політехнічний університет (ОНПУ)",
					"alias": ""
			},
			"807": {
					"id": 807,
					"name": "Одеський національний університет ім. Мечникова (ОНУ)",
					"alias": ""
			},
			"808": {
					"id": 808,
					"name": "Одеський регіональний інститут державного управління НАДУ",
					"alias": ""
			},
			"809": {
					"id": 809,
					"name": "Одеський торговельно-економічний інститут Київського національного торговельно-економічного університету (ОТЕІ КНТЕУ)",
					"alias": ""
			},
			"810": {
					"id": 810,
					"name": "Первомайський інститут Одеського національного університету ім. Мечникова",
					"alias": ""
			},
			"811": {
					"id": 811,
					"name": "Первомайський політехнічний інститут НУК",
					"alias": ""
			},
			"812": {
					"id": 812,
					"name": "Південноукраїнський національний педагогічний університет ім. К. Д. Ушинського",
					"alias": ""
			},
			"813": {
					"id": 813,
					"name": "Подільський державний аграрно-технічний університет (ПДАТУ)",
					"alias": ""
			},
			"814": {
					"id": 814,
					"name": "Полтавська державна аграрна академія (ПДАА)",
					"alias": ""
			},
			"815": {
					"id": 815,
					"name": "Полтавська філія Національного університету харчових технологій",
					"alias": ""
			},
			"816": {
					"id": 816,
					"name": "Полтавський національний педагогічний університет ім. Короленка (ПНПУ)",
					"alias": ""
			},
			"817": {
					"id": 817,
					"name": "Полтавський національний технічний університет ім. Кондратюка (ПНТУ)",
					"alias": ""
			},
			"818": {
					"id": 818,
					"name": "Полтавський юридичний інститут Національного юридичного університету імені Ярослава Мудрого",
					"alias": ""
			},
			"819": {
					"id": 819,
					"name": "Приазовський державний технічний університет (ПДТУ)",
					"alias": ""
			},
			"820": {
					"id": 820,
					"name": "Придніпровська державна академія будівництва та архітектури (ПДАБА)",
					"alias": ""
			},
			"821": {
					"id": 821,
					"name": "Придніпровська державна академія фізичної культури і спорту",
					"alias": ""
			},
			"822": {
					"id": 822,
					"name": "Прикарпатський національний університет імені Василя Стефаника (ПНУ)",
					"alias": ""
			},
			"823": {
					"id": 823,
					"name": "Рівненський державний гуманітарний університет (РДГУ)",
					"alias": ""
			},
			"824": {
					"id": 824,
					"name": "Севастопольський економіко-гуманітарний інститут ТНУ",
					"alias": ""
			},
			"825": {
					"id": 825,
					"name": "Севастопольський міський гуманітарний університет (СевМГУ)",
					"alias": ""
			},
			"826": {
					"id": 826,
					"name": "Севастопольський національний технічний університет (СевНТУ)",
					"alias": ""
			},
			"827": {
					"id": 827,
					"name": "Севастопольський національний університет ядерної енергії та промисловості (СНУЯЕтаП)",
					"alias": ""
			},
			"828": {
					"id": 828,
					"name": "Стахановський навчально-науковий інститут гірничих та освітніх технологій Української інженерно-педагогічної академії",
					"alias": ""
			},
			"829": {
					"id": 829,
					"name": "Сумський державний педагогічний університет імені Макаренка (СумДПУ)",
					"alias": ""
			},
			"830": {
					"id": 830,
					"name": "Сумський державний університет (СумДУ)",
					"alias": ""
			},
			"831": {
					"id": 831,
					"name": "Сумський національний аграрний університет (СНАУ)",
					"alias": ""
			},
			"832": {
					"id": 832,
					"name": "Східний ЛЦДЗН Національного університету водного господарства та природокористування",
					"alias": ""
			},
			"833": {
					"id": 833,
					"name": "Східноєвропейський національний університет ім. Л. Українки",
					"alias": ""
			},
			"834": {
					"id": 834,
					"name": "Східноукраїнський національний університет ім. Даля (СНУ)",
					"alias": ""
			},
			"835": {
					"id": 835,
					"name": "Таврійський державний агротехнологічний університет (ТДАТУ)",
					"alias": ""
			},
			"836": {
					"id": 836,
					"name": "Таврійський національний університет ім. В. Вернадського (ТНУ)",
					"alias": ""
			},
			"837": {
					"id": 837,
					"name": "Таврійський національний університет імені В. І. Вернадського (ТНУ)",
					"alias": ""
			},
			"838": {
					"id": 838,
					"name": "Тернопільський державний медичний університет ім. Горбачевського (ТДМУ)",
					"alias": ""
			},
			"839": {
					"id": 839,
					"name": "Тернопільський національний економічний університет (ТНЕУ)",
					"alias": ""
			},
			"840": {
					"id": 840,
					"name": "Тернопільський національний педагогічний університет ім. В. Гнатюка (ТНПУ)",
					"alias": ""
			},
			"841": {
					"id": 841,
					"name": "Тернопільський національний технічний університет ім. Пулюя (ТНТУ)",
					"alias": ""
			},
			"842": {
					"id": 842,
					"name": "Технологічний інститут Східноукраїнського національного університету ім. Даля",
					"alias": ""
			},
			"843": {
					"id": 843,
					"name": "Ужгородський національний університет (УжНУ)",
					"alias": ""
			},
			"844": {
					"id": 844,
					"name": "Ужгородський торговельно-економічний інститут Київського національного торговельно-економічного університету (УТЕІ КНТЕУ)",
					"alias": ""
			},
			"845": {
					"id": 845,
					"name": "Українська академія банківської справи Національного банку України (УАБС НБУ)",
					"alias": ""
			},
			"846": {
					"id": 846,
					"name": "Українська академія печати (УАД)",
					"alias": ""
			},
			"847": {
					"id": 847,
					"name": "Українська інженерно-педагогічна академія (УІПА)",
					"alias": ""
			},
			"848": {
					"id": 848,
					"name": "Українська медична стоматологічна академія (УМСА)",
					"alias": ""
			},
			"849": {
					"id": 849,
					"name": "Український державний університет залізничного транспорту",
					"alias": ""
			},
			"850": {
					"id": 850,
					"name": "Український державний хіміко-технологічний університет (УДХТУ)",
					"alias": ""
			},
			"851": {
					"id": 851,
					"name": "Уманський державний педагогічний університет імені Павла Тичини (УДПУ)",
					"alias": ""
			},
			"852": {
					"id": 852,
					"name": "Уманський національний університет садівництва (УНУС)",
					"alias": ""
			},
			"853": {
					"id": 853,
					"name": "Університет \"Україна\" Тернопіль",
					"alias": ""
			},
			"854": {
					"id": 854,
					"name": "Університет державної фіскальної служби України (УДФСУ)",
					"alias": ""
			},
			"855": {
					"id": 855,
					"name": "Університет менеджменту освіти (УМО) Національної Академії педагогічних наук України",
					"alias": ""
			},
			"856": {
					"id": 856,
					"name": "Університет митної справи та фінансів",
					"alias": ""
			},
			"857": {
					"id": 857,
					"name": "Факультет соціології і права КПІ ім. Ігоря Сікорського",
					"alias": ""
			},
			"858": {
					"id": 858,
					"name": "Феодосійське відділення Кримського факультету Східноукраїнського національного університету ім. Даля (ФВКФ СНУ)",
					"alias": ""
			},
			"859": {
					"id": 859,
					"name": "Філія республіканського вищого навчального закладу «Кримський гуманітарний університет»",
					"alias": ""
			},
			"860": {
					"id": 860,
					"name": "Харківська гуманітарно-педагогічна академія",
					"alias": ""
			},
			"861": {
					"id": 861,
					"name": "Харківська державна академія дизайну і мистецтв (ХДАДМ)",
					"alias": ""
			},
			"862": {
					"id": 862,
					"name": "Харківська державна академія культури (ХДАК)",
					"alias": ""
			},
			"863": {
					"id": 863,
					"name": "Харківська державна академія фізичної культури (ХДАФК)",
					"alias": ""
			},
			"864": {
					"id": 864,
					"name": "Харківська державна зооветеринарна академія (ХДЗВА)",
					"alias": ""
			},
			"865": {
					"id": 865,
					"name": "Харківський державний університет харчування та торгівлі (ХДУХТ)",
					"alias": ""
			},
			"866": {
					"id": 866,
					"name": "Харківський інститут фінансів Українського державного університету фінансів та міжнародної торгівлі (ХІФ)",
					"alias": ""
			},
			"867": {
					"id": 867,
					"name": "Харківський навчально-науковий інститут ДВНЗ \"Університет банківської справи\"",
					"alias": ""
			},
			"868": {
					"id": 868,
					"name": "Харківський національний автомобільно-дорожній університет (ХНАДУ)",
					"alias": ""
			},
			"869": {
					"id": 869,
					"name": "Харківський національний аграрний університет ім. Докучаєва (ХНАУ)",
					"alias": ""
			},
			"870": {
					"id": 870,
					"name": "Харківський національний економічний університет імені Семена Кузнеця (ХНЕУ ім. С. Кузнеця)",
					"alias": ""
			},
			"871": {
					"id": 871,
					"name": "Харківський національний медичний університет (ХНМУ)",
					"alias": ""
			},
			"872": {
					"id": 872,
					"name": "Харківський національний педагогічний університет ім. Сковороди (ХНПУ)",
					"alias": ""
			},
			"873": {
					"id": 873,
					"name": "Харківський національний технічний університет сільського господарства ім. Василенка (ХНТУСГ)",
					"alias": ""
			},
			"874": {
					"id": 874,
					"name": "Харківський національний університет будівництва та архітектури (ХНУБА)",
					"alias": ""
			},
			"875": {
					"id": 875,
					"name": "Харківський національний університет внутрішніх справ (ХНУВС)",
					"alias": ""
			},
			"876": {
					"id": 876,
					"name": "Харківський національний університет ім. Каразіна (ХНУ)",
					"alias": ""
			},
			"877": {
					"id": 877,
					"name": "Харківський національний університет мистецтв ім. Котляревського (ХНУМ)",
					"alias": ""
			},
			"878": {
					"id": 878,
					"name": "Харківський національний університет міського господарства (ХНУМГ)",
					"alias": ""
			},
			"879": {
					"id": 879,
					"name": "Харківський національний університет міського господарства імені О.М. Бекетова",
					"alias": ""
			},
			"880": {
					"id": 880,
					"name": "Харківський національний університет Повітряних Сил ім. Кожедуба (ХНУПС)",
					"alias": ""
			},
			"881": {
					"id": 881,
					"name": "Харківський національний університет радіоелектроніки (ХНУРЕ)",
					"alias": ""
			},
			"882": {
					"id": 882,
					"name": "Харківський регіональний інститут державного управління НАДУ",
					"alias": ""
			},
			"883": {
					"id": 883,
					"name": "Харківський торговельно-економічний інститут КНТЕУ",
					"alias": ""
			},
			"884": {
					"id": 884,
					"name": "Херсонська державна морська академія (ХДМА)",
					"alias": ""
			},
			"885": {
					"id": 885,
					"name": "Херсонський державний аграрний університет (ХДАУ)",
					"alias": ""
			},
			"886": {
					"id": 886,
					"name": "Херсонський державний університет (ХДУ)",
					"alias": ""
			},
			"887": {
					"id": 887,
					"name": "Херсонський національний технічний університет (ХНТУ)",
					"alias": ""
			},
			"888": {
					"id": 888,
					"name": "Херсонський факультет Одеського державного університету внутрішніх справ",
					"alias": ""
			},
			"889": {
					"id": 889,
					"name": "Хмельницька гуманітарно-педагогічна академія (ХГПА)м. Хмельницький",
					"alias": ""
			},
			"890": {
					"id": 890,
					"name": "Хмельницька філія Донецького національного університету імені Василя Стуса «Бізнес-інноваційний центр «ДонНУ-Поділля»",
					"alias": ""
			},
			"891": {
					"id": 891,
					"name": "Хмельницький кооперативний торговельно-економічний інститут (ХКТЕІ)",
					"alias": ""
			},
			"892": {
					"id": 892,
					"name": "Хмельницький національний університет (ХНУ)",
					"alias": ""
			},
			"893": {
					"id": 893,
					"name": "Хмельницький університет управління та права (ХУУП)",
					"alias": ""
			},
			"894": {
					"id": 894,
					"name": "Хустський навчально-консультаційний центр НУ \"Львівська політехніка\"",
					"alias": ""
			},
			"895": {
					"id": 895,
					"name": "Центральноукраїнський національний технічний університет (ЦНТУ)",
					"alias": ""
			},
			"896": {
					"id": 896,
					"name": "Черкаський державний технологічний університет (ЧДТУ)",
					"alias": ""
			},
			"897": {
					"id": 897,
					"name": "Черкаський заочний факультет Полтавського університету споживчої кооперації України",
					"alias": ""
			},
			"898": {
					"id": 898,
					"name": "Черкаський інститут пожежної безпеки ім. Героїв Чорнобиля (ЧІПБ)",
					"alias": ""
			},
			"899": {
					"id": 899,
					"name": "Черкаський навчально-науковий інститут ДВНЗ \"Університет банківської справи\"",
					"alias": ""
			},
			"900": {
					"id": 900,
					"name": "Черкаський національний університет ім. Хмельницького (ЧНУ)",
					"alias": ""
			},
			"901": {
					"id": 901,
					"name": "Чернівецький національний університет ім. Федьковича (ЧНУ)",
					"alias": ""
			},
			"902": {
					"id": 902,
					"name": "Чернівецький торговельно-економічний інститут КНТЕУ",
					"alias": ""
			},
			"903": {
					"id": 903,
					"name": "Чернігівський державний інститут економіки і управління (ЧДІЕУ)",
					"alias": ""
			},
			"904": {
					"id": 904,
					"name": "Чернігівський державний інститут права",
					"alias": ""
			},
			"905": {
					"id": 905,
					"name": "Чернігівський національний педагогічний університет ім. Шевченка (ЧНПУ)",
					"alias": ""
			},
			"906": {
					"id": 906,
					"name": "Чернігівський національний технологічний університет (ЧНТУ)",
					"alias": ""
			},
			"907": {
					"id": 907,
					"name": "Чорноморський національний університет імені Петра Могили (ЧНУ ім. П. Могили)",
					"alias": ""
			}
	},
	"university_degrees": {
			"1": {
					"id": 1,
					"name": "студент",
					"alias": ""
			},
			"2": {
					"id": 2,
					"name": "бакалавр",
					"alias": ""
			},
			"3": {
					"id": 3,
					"name": "спеціаліст",
					"alias": ""
			},
			"4": {
					"id": 4,
					"name": "магістр",
					"alias": ""
			},
			"5": {
					"id": 5,
					"name": "аспірант",
					"alias": ""
			},
			"6": {
					"id": 6,
					"name": "кандидат наук (PhD)",
					"alias": ""
			},
			"7": {
					"id": 7,
					"name": "доктор наук",
					"alias": ""
			},
			"8": {
					"id": 8,
					"name": "професор",
					"alias": ""
			}
	},
	"langs": {
			"1": {
					"id": 1,
					"name": "українська",
					"alias": ""
			},
			"2": {
					"id": 2,
					"name": "російська",
					"alias": ""
			},
			"3": {
					"id": 3,
					"name": "англійська",
					"alias": ""
			}
	}
}